{"files":{"GitHub Pages.md":{"filePath":"GitHub Pages.md","links":[],"meta":{"page":{"description":"GitHub Pages is an easy way to deploy and host static websites on GitHub."},"slug":"github-pages","tags":[]},"parentNote":"index.md","title":"GitHub Pages","url":"github-pages.html"},"index.md":{"filePath":"index.md","links":[],"meta":{"page":{"description":"Welcome to my public Zettelkasten. This is a place to store things that are interesting and help me remember them."},"tags":[]},"parentNote":null,"title":"Welcome","url":""},"page2.md":{"filePath":"page2.md","links":[],"meta":{"page":{"description":"Will this show?"},"tags":[]},"parentNote":"index.md","title":"Page 2","url":"page2.html"}},"version":1}